[
  {
    "ID": 1,
    "WinRate": null,
    "Quest": "20-11",
    "Position1": "Amleth",
    "Position1Rank": null,
    "Position1Level": null,
    "Position2": "Florence",
    "Position2Rank": null,
    "Position2Level": null,
    "Position3": "Mimi",
    "Position3Rank": null,
    "Position3Level": null,
    "Position4": "Primavera",
    "Position4Rank": null,
    "Position4Level": null,
    "Position5": "Matilda",
    "Position5Rank": null,
    "Position5Level": null,
    "Memo": ""
  },
  {
    "ID": 2,
    "WinRate": null,
    "Quest": "20-16",
    "Position1": "Cordie",
    "Position1Rank": null,
    "Position1Level": null,
    "Position2": "Lunalynn",
    "Position2Rank": null,
    "Position2Level": null,
    "Position3": "Merlyn",
    "Position3Rank": null,
    "Position3Level": null,
    "Position4": "Florence",
    "Position4Rank": null,
    "Position4Level": null,
    "Position5": "Matilda",
    "Position5Rank": null,
    "Position5Level": null,
    "Memo": ""
  },
  {
    "ID": 3,
    "WinRate": null,
    "Quest": "20-17",
    "Position1": null,
    "Position1Rank": null,
    "Position1Level": null,
    "Position2": null,
    "Position2Rank": null,
    "Position2Level": null,
    "Position3": null,
    "Position3Rank": null,
    "Position3Level": null,
    "Position4": null,
    "Position4Rank": null,
    "Position4Level": null,
    "Position5": null,
    "Position5Rank": null,
    "Position5Level": null,
    "Memo": ""
  },
  {
    "ID": 4,
    "WinRate": null,
    "Quest": "135",
    "Position1": "Olivia",
    "Position1Rank": "SR+",
    "Position1Level": 180,
    "Position2": "Tropon",
    "Position2Rank": "SR+",
    "Position2Level": 180,
    "Position3": "Primavera",
    "Position3Rank": "UR",
    "Position3Level": 180,
    "Position4": "Hathor",
    "Position4Rank": "SR+",
    "Position4Level": 180,
    "Position5": "Mimi",
    "Position5Rank": "SR",
    "Position5Level": 180,
    "Memo": ""
  },
  {
    "ID": 5,
    "WinRate": null,
    "Quest": "140",
    "Position1": "Olivia",
    "Position1Rank": "SR+",
    "Position1Level": 180,
    "Position2": "Mimi",
    "Position2Rank": "SR",
    "Position2Level": 180,
    "Position3": "Primavera",
    "Position3Rank": "UR",
    "Position3Level": 180,
    "Position4": "Tropon",
    "Position4Rank": "SR+",
    "Position4Level": 180,
    "Position5": "Hathor",
    "Position5Rank": "SR+",
    "Position5Level": 180,
    "Memo": "調整托波波防最高和咪咪肪最低"
  },
  {
    "ID": 6,
    "WinRate": null,
    "Quest": "141",
    "Position1": "Tropon",
    "Position1Rank": "SR+",
    "Position1Level": 180,
    "Position2": "Hathor",
    "Position2Rank": "SR+",
    "Position2Level": 180,
    "Position3": "Primavera",
    "Position3Rank": "UR",
    "Position3Level": 180,
    "Position4": "Olivia",
    "Position4Rank": "SR+",
    "Position4Level": 180,
    "Position5": "Mimi",
    "Position5Rank": "SR",
    "Position5Level": 180,
    "Memo": ""
  },
  {
    "ID": 7,
    "WinRate": null,
    "Quest": "192",
    "Position1": "Amleth",
    "Position1Rank": "UR",
    "Position1Level": 180,
    "Position2": "Soltina",
    "Position2Rank": "SR+",
    "Position2Level": 180,
    "Position3": "Florence",
    "Position3Rank": "LR+2",
    "Position3Level": 220,
    "Position4": "Fenrir",
    "Position4Rank": "SR+",
    "Position4Level": 180,
    "Position5": "Iris",
    "Position5Rank": "SR+",
    "Position5Level": 160,
    "Memo": ""
  },
  {
    "ID": 8,
    "WinRate": null,
    "Quest": "195",
    "Position1": "Iris",
    "Position1Rank": "SR+",
    "Position1Level": 160,
    "Position2": "Soltina",
    "Position2Rank": "SR+",
    "Position2Level": 180,
    "Position3": "Florence",
    "Position3Rank": "LR+2",
    "Position3Level": 220,
    "Position4": "Fenrir",
    "Position4Rank": "SR+",
    "Position4Level": 180,
    "Position5": "Amleth",
    "Position5Rank": "UR",
    "Position5Level": 180,
    "Memo": ""
  },
  {
    "ID": 9,
    "WinRate": null,
    "Quest": "198",
    "Position1": "Soltina",
    "Position1Rank": "SR+",
    "Position1Level": 160,
    "Position2": "Iris",
    "Position2Rank": "SR+",
    "Position2Level": 160,
    "Position3": "Amleth",
    "Position3Rank": "UR",
    "Position3Level": 180,
    "Position4": "Fenrir",
    "Position4Rank": "SR+",
    "Position4Level": 180,
    "Position5": "Florence",
    "Position5Rank": "LR+2",
    "Position5Level": 220,
    "Memo": ""
  },
  {
    "ID": 10,
    "WinRate": "< 1%",
    "Quest": "208",
    "Position1": "Iris",
    "Position1Rank": "SR+",
    "Position1Level": 160,
    "Position2": "Amleth",
    "Position2Rank": "UR",
    "Position2Level": 180,
    "Position3": "Soltina",
    "Position3Rank": "SR+",
    "Position3Level": 180,
    "Position4": "Florence",
    "Position4Rank": "LR+2",
    "Position4Level": 220,
    "Position5": "Illya",
    "Position5Rank": "SR+",
    "Position5Level": 160,
    "Memo": ""
  }
]